<?xml version="1.0" encoding="UTF-8"?>
<tv>
  <channel id="ClubberTV.ie">
    <display-name>Clubber TV</display-name>
    <desc>Local GAA action</desc>
  </channel>

  <programme start="20250125004556 " stop="20250125024556 " channel="ClubberTV.ie">
    <title>Clubber TV</title>
    <desc>Local GAA action</desc>
  </programme>

  <programme start="20250125024556 " stop="20250125044556 " channel="ClubberTV.ie">
    <title>Clubber TV</title>
    <desc>Local GAA action</desc>
  </programme>

  <programme start="20250125044556 " stop="20250125064556 " channel="ClubberTV.ie">
    <title>Clubber TV</title>
    <desc>Local GAA action</desc>
  </programme>

  <programme start="20250125064556 " stop="20250125084556 " channel="ClubberTV.ie">
    <title>Clubber TV</title>
    <desc>Local GAA action</desc>
  </programme>

  <programme start="20250125084556 " stop="20250125104556 " channel="ClubberTV.ie">
    <title>Clubber TV</title>
    <desc>Local GAA action</desc>
  </programme>

  <programme start="20250125104556 " stop="20250125124556 " channel="ClubberTV.ie">
    <title>Clubber TV</title>
    <desc>Local GAA action</desc>
  </programme>

  <programme start="20250125124556 " stop="20250125144556 " channel="ClubberTV.ie">
    <title>Clubber TV</title>
    <desc>Local GAA action</desc>
  </programme>

  <programme start="20250125144556 " stop="20250125164556 " channel="ClubberTV.ie">
    <title>Clubber TV</title>
    <desc>Local GAA action</desc>
  </programme>

  <programme start="20250125164556 " stop="20250125184556 " channel="ClubberTV.ie">
    <title>Clubber TV</title>
    <desc>Local GAA action</desc>
  </programme>

  <programme start="20250125184556 " stop="20250125204556 " channel="ClubberTV.ie">
    <title>Clubber TV</title>
    <desc>Local GAA action</desc>
  </programme>

  <programme start="20250125204556 " stop="20250125224556 " channel="ClubberTV.ie">
    <title>Clubber TV</title>
    <desc>Local GAA action</desc>
  </programme>

  <programme start="20250125224556 " stop="20250126004556 " channel="ClubberTV.ie">
    <title>Clubber TV</title>
    <desc>Local GAA action</desc>
  </programme>

  <programme start="20250126004556 " stop="20250126024556 " channel="ClubberTV.ie">
    <title>Clubber TV</title>
    <desc>Local GAA action</desc>
  </programme>

  <programme start="20250126024556 " stop="20250126044556 " channel="ClubberTV.ie">
    <title>Clubber TV</title>
    <desc>Local GAA action</desc>
  </programme>

  <programme start="20250126044556 " stop="20250126064556 " channel="ClubberTV.ie">
    <title>Clubber TV</title>
    <desc>Local GAA action</desc>
  </programme>

  <programme start="20250126064556 " stop="20250126084556 " channel="ClubberTV.ie">
    <title>Clubber TV</title>
    <desc>Local GAA action</desc>
  </programme>

  <programme start="20250126084556 " stop="20250126104556 " channel="ClubberTV.ie">
    <title>Clubber TV</title>
    <desc>Local GAA action</desc>
  </programme>

  <programme start="20250126104556 " stop="20250126124556 " channel="ClubberTV.ie">
    <title>Clubber TV</title>
    <desc>Local GAA action</desc>
  </programme>

  <programme start="20250126124556 " stop="20250126144556 " channel="ClubberTV.ie">
    <title>Clubber TV</title>
    <desc>Local GAA action</desc>
  </programme>

  <programme start="20250126144556 " stop="20250126164556 " channel="ClubberTV.ie">
    <title>Clubber TV</title>
    <desc>Local GAA action</desc>
  </programme>

  <programme start="20250126164556 " stop="20250126184556 " channel="ClubberTV.ie">
    <title>Clubber TV</title>
    <desc>Local GAA action</desc>
  </programme>

  <programme start="20250126184556 " stop="20250126204556 " channel="ClubberTV.ie">
    <title>Clubber TV</title>
    <desc>Local GAA action</desc>
  </programme>

  <programme start="20250126204556 " stop="20250126224556 " channel="ClubberTV.ie">
    <title>Clubber TV</title>
    <desc>Local GAA action</desc>
  </programme>

  <programme start="20250126224556 " stop="20250127004556 " channel="ClubberTV.ie">
    <title>Clubber TV</title>
    <desc>Local GAA action</desc>
  </programme>

  <programme start="20250127004556 " stop="20250127024556 " channel="ClubberTV.ie">
    <title>Clubber TV</title>
    <desc>Local GAA action</desc>
  </programme>

  <programme start="20250127024556 " stop="20250127044556 " channel="ClubberTV.ie">
    <title>Clubber TV</title>
    <desc>Local GAA action</desc>
  </programme>

  <programme start="20250127044556 " stop="20250127064556 " channel="ClubberTV.ie">
    <title>Clubber TV</title>
    <desc>Local GAA action</desc>
  </programme>

  <programme start="20250127064556 " stop="20250127084556 " channel="ClubberTV.ie">
    <title>Clubber TV</title>
    <desc>Local GAA action</desc>
  </programme>

  <programme start="20250127084556 " stop="20250127104556 " channel="ClubberTV.ie">
    <title>Clubber TV</title>
    <desc>Local GAA action</desc>
  </programme>

  <programme start="20250127104556 " stop="20250127124556 " channel="ClubberTV.ie">
    <title>Clubber TV</title>
    <desc>Local GAA action</desc>
  </programme>

  <programme start="20250127124556 " stop="20250127144556 " channel="ClubberTV.ie">
    <title>Clubber TV</title>
    <desc>Local GAA action</desc>
  </programme>

  <programme start="20250127144556 " stop="20250127164556 " channel="ClubberTV.ie">
    <title>Clubber TV</title>
    <desc>Local GAA action</desc>
  </programme>

  <programme start="20250127164556 " stop="20250127184556 " channel="ClubberTV.ie">
    <title>Clubber TV</title>
    <desc>Local GAA action</desc>
  </programme>

  <programme start="20250127184556 " stop="20250127204556 " channel="ClubberTV.ie">
    <title>Clubber TV</title>
    <desc>Local GAA action</desc>
  </programme>

  <programme start="20250127204556 " stop="20250127224556 " channel="ClubberTV.ie">
    <title>Clubber TV</title>
    <desc>Local GAA action</desc>
  </programme>

  <programme start="20250127224556 " stop="20250128004556 " channel="ClubberTV.ie">
    <title>Clubber TV</title>
    <desc>Local GAA action</desc>
  </programme>

  <programme start="20250128004556 " stop="20250128024556 " channel="ClubberTV.ie">
    <title>Clubber TV</title>
    <desc>Local GAA action</desc>
  </programme>

  <programme start="20250128024556 " stop="20250128044556 " channel="ClubberTV.ie">
    <title>Clubber TV</title>
    <desc>Local GAA action</desc>
  </programme>

  <programme start="20250128044556 " stop="20250128064556 " channel="ClubberTV.ie">
    <title>Clubber TV</title>
    <desc>Local GAA action</desc>
  </programme>

  <programme start="20250128064556 " stop="20250128084556 " channel="ClubberTV.ie">
    <title>Clubber TV</title>
    <desc>Local GAA action</desc>
  </programme>

  <programme start="20250128084556 " stop="20250128104556 " channel="ClubberTV.ie">
    <title>Clubber TV</title>
    <desc>Local GAA action</desc>
  </programme>

  <programme start="20250128104556 " stop="20250128124556 " channel="ClubberTV.ie">
    <title>Clubber TV</title>
    <desc>Local GAA action</desc>
  </programme>

  <programme start="20250128124556 " stop="20250128144556 " channel="ClubberTV.ie">
    <title>Clubber TV</title>
    <desc>Local GAA action</desc>
  </programme>

  <programme start="20250128144556 " stop="20250128164556 " channel="ClubberTV.ie">
    <title>Clubber TV</title>
    <desc>Local GAA action</desc>
  </programme>

  <programme start="20250128164556 " stop="20250128184556 " channel="ClubberTV.ie">
    <title>Clubber TV</title>
    <desc>Local GAA action</desc>
  </programme>

  <programme start="20250128184556 " stop="20250128204556 " channel="ClubberTV.ie">
    <title>Clubber TV</title>
    <desc>Local GAA action</desc>
  </programme>

  <programme start="20250128204556 " stop="20250128224556 " channel="ClubberTV.ie">
    <title>Clubber TV</title>
    <desc>Local GAA action</desc>
  </programme>

  <programme start="20250128224556 " stop="20250129004556 " channel="ClubberTV.ie">
    <title>Clubber TV</title>
    <desc>Local GAA action</desc>
  </programme>

  <programme start="20250129004556 " stop="20250129024556 " channel="ClubberTV.ie">
    <title>Clubber TV</title>
    <desc>Local GAA action</desc>
  </programme>

  <programme start="20250129024556 " stop="20250129044556 " channel="ClubberTV.ie">
    <title>Clubber TV</title>
    <desc>Local GAA action</desc>
  </programme>

  <programme start="20250129044556 " stop="20250129064556 " channel="ClubberTV.ie">
    <title>Clubber TV</title>
    <desc>Local GAA action</desc>
  </programme>

  <programme start="20250129064556 " stop="20250129084556 " channel="ClubberTV.ie">
    <title>Clubber TV</title>
    <desc>Local GAA action</desc>
  </programme>

  <programme start="20250129084556 " stop="20250129104556 " channel="ClubberTV.ie">
    <title>Clubber TV</title>
    <desc>Local GAA action</desc>
  </programme>

  <programme start="20250129104556 " stop="20250129124556 " channel="ClubberTV.ie">
    <title>Clubber TV</title>
    <desc>Local GAA action</desc>
  </programme>

  <programme start="20250129124556 " stop="20250129144556 " channel="ClubberTV.ie">
    <title>Clubber TV</title>
    <desc>Local GAA action</desc>
  </programme>

  <programme start="20250129144556 " stop="20250129164556 " channel="ClubberTV.ie">
    <title>Clubber TV</title>
    <desc>Local GAA action</desc>
  </programme>

  <programme start="20250129164556 " stop="20250129184556 " channel="ClubberTV.ie">
    <title>Clubber TV</title>
    <desc>Local GAA action</desc>
  </programme>

  <programme start="20250129184556 " stop="20250129204556 " channel="ClubberTV.ie">
    <title>Clubber TV</title>
    <desc>Local GAA action</desc>
  </programme>

  <programme start="20250129204556 " stop="20250129224556 " channel="ClubberTV.ie">
    <title>Clubber TV</title>
    <desc>Local GAA action</desc>
  </programme>

  <programme start="20250129224556 " stop="20250130004556 " channel="ClubberTV.ie">
    <title>Clubber TV</title>
    <desc>Local GAA action</desc>
  </programme>

  <programme start="20250130004556 " stop="20250130024556 " channel="ClubberTV.ie">
    <title>Clubber TV</title>
    <desc>Local GAA action</desc>
  </programme>

  <programme start="20250130024556 " stop="20250130044556 " channel="ClubberTV.ie">
    <title>Clubber TV</title>
    <desc>Local GAA action</desc>
  </programme>

  <programme start="20250130044556 " stop="20250130064556 " channel="ClubberTV.ie">
    <title>Clubber TV</title>
    <desc>Local GAA action</desc>
  </programme>

  <programme start="20250130064556 " stop="20250130084556 " channel="ClubberTV.ie">
    <title>Clubber TV</title>
    <desc>Local GAA action</desc>
  </programme>

  <programme start="20250130084556 " stop="20250130104556 " channel="ClubberTV.ie">
    <title>Clubber TV</title>
    <desc>Local GAA action</desc>
  </programme>

  <programme start="20250130104556 " stop="20250130124556 " channel="ClubberTV.ie">
    <title>Clubber TV</title>
    <desc>Local GAA action</desc>
  </programme>

  <programme start="20250130124556 " stop="20250130144556 " channel="ClubberTV.ie">
    <title>Clubber TV</title>
    <desc>Local GAA action</desc>
  </programme>

  <programme start="20250130144556 " stop="20250130164556 " channel="ClubberTV.ie">
    <title>Clubber TV</title>
    <desc>Local GAA action</desc>
  </programme>

  <programme start="20250130164556 " stop="20250130184556 " channel="ClubberTV.ie">
    <title>Clubber TV</title>
    <desc>Local GAA action</desc>
  </programme>

  <programme start="20250130184556 " stop="20250130204556 " channel="ClubberTV.ie">
    <title>Clubber TV</title>
    <desc>Local GAA action</desc>
  </programme>

  <programme start="20250130204556 " stop="20250130224556 " channel="ClubberTV.ie">
    <title>Clubber TV</title>
    <desc>Local GAA action</desc>
  </programme>

  <programme start="20250130224556 " stop="20250131004556 " channel="ClubberTV.ie">
    <title>Clubber TV</title>
    <desc>Local GAA action</desc>
  </programme>

  <programme start="20250131004556 " stop="20250131024556 " channel="ClubberTV.ie">
    <title>Clubber TV</title>
    <desc>Local GAA action</desc>
  </programme>

  <programme start="20250131024556 " stop="20250131044556 " channel="ClubberTV.ie">
    <title>Clubber TV</title>
    <desc>Local GAA action</desc>
  </programme>

  <programme start="20250131044556 " stop="20250131064556 " channel="ClubberTV.ie">
    <title>Clubber TV</title>
    <desc>Local GAA action</desc>
  </programme>

  <programme start="20250131064556 " stop="20250131084556 " channel="ClubberTV.ie">
    <title>Clubber TV</title>
    <desc>Local GAA action</desc>
  </programme>

  <programme start="20250131084556 " stop="20250131104556 " channel="ClubberTV.ie">
    <title>Clubber TV</title>
    <desc>Local GAA action</desc>
  </programme>

  <programme start="20250131104556 " stop="20250131124556 " channel="ClubberTV.ie">
    <title>Clubber TV</title>
    <desc>Local GAA action</desc>
  </programme>

  <programme start="20250131124556 " stop="20250131144556 " channel="ClubberTV.ie">
    <title>Clubber TV</title>
    <desc>Local GAA action</desc>
  </programme>

  <programme start="20250131144556 " stop="20250131164556 " channel="ClubberTV.ie">
    <title>Clubber TV</title>
    <desc>Local GAA action</desc>
  </programme>

  <programme start="20250131164556 " stop="20250131184556 " channel="ClubberTV.ie">
    <title>Clubber TV</title>
    <desc>Local GAA action</desc>
  </programme>

  <programme start="20250131184556 " stop="20250131204556 " channel="ClubberTV.ie">
    <title>Clubber TV</title>
    <desc>Local GAA action</desc>
  </programme>

  <programme start="20250131204556 " stop="20250131224556 " channel="ClubberTV.ie">
    <title>Clubber TV</title>
    <desc>Local GAA action</desc>
  </programme>

  <programme start="20250131224556 " stop="20250201004556 " channel="ClubberTV.ie">
    <title>Clubber TV</title>
    <desc>Local GAA action</desc>
  </programme>
</tv>